{
  "type": "Feature",
  "properties": {
    "gn:asciiname":"Motutapu",
    "gn:country_code":"NU",
    "gn:dem":54,
    "gn:feature_class":"P",
    "gn:feature_code":"PPL",
    "gn:name":"Motutapu",
    "gn:population":0,
    "gn:timezone":"Pacific/Niue",
    "iso:country":"NU",
    "wof:name":"Motutapu",
    "wof:placetype":"locality"
},
  "geometry": {"coordinates":[-169.88683,-19.02967],"type":"Point"}
}