{
  "type": "Feature",
  "properties": {
    "gn:country":"NU",
    "gn:fcode":"PPL",
    "gn:pop":63,
    "iso:country":"NU",
    "qs:name":"Hikutivake",
    "qs:photos_9r":0,
    "qs:photos_sr":0,
    "qs:pop_sr":"1",
    "wof:name":"Hikutivake",
    "wof:placetype":"locality",
    "wof:population":63
},
  "geometry": {"coordinates":[-169.88333,-18.93333],"type":"Point"}
}