{
  "type": "Feature",
  "properties": {
    "gn:asciiname":"Avatele",
    "gn:country_code":"NU",
    "gn:dem":29,
    "gn:feature_class":"P",
    "gn:feature_code":"PPL",
    "gn:name":"Avatele",
    "gn:population":0,
    "gn:timezone":"Pacific/Niue",
    "iso:country":"NU",
    "wof:name":"Avatele",
    "wof:placetype":"locality"
},
  "geometry": {"coordinates":[-169.91138000000001,-19.12449],"type":"Point"}
}