{
  "type": "Feature",
  "properties": {
    "gn:asciiname":"Avatele",
    "gn:country_code":"NU",
    "gn:dem":29,
    "gn:feature_class":"P",
    "gn:feature_code":"PPL",
    "gn:name":"Avatele",
    "gn:population":0,
    "gn:timezone":"Pacific/Niue",
    "iso:country":"NU",
    "name:ceb_x_preferred":[
        "Avatele"
    ],
    "name:deu_x_preferred":[
        "Avatele"
    ],
    "name:fra_x_preferred":[
        "Avatele"
    ],
    "name:hun_x_preferred":[
        "Avatele"
    ],
    "name:ita_x_preferred":[
        "Avatele"
    ],
    "name:jpn_x_preferred":[
        "\u30a2\u30d0\u30c6\u30ec"
    ],
    "name:nld_x_preferred":[
        "Avatele"
    ],
    "name:pol_x_preferred":[
        "Avatele"
    ],
    "name:rus_x_preferred":[
        "\u0410\u0432\u0430\u0442\u0435\u043b\u0435"
    ],
    "name:spa_x_preferred":[
        "Avatele"
    ],
    "name:ukr_x_preferred":[
        "\u0410\u0432\u0430\u0442\u0435\u043b\u0435"
    ],
    "wof:name":"Avatele",
    "wof:placetype":"locality"
},
  "geometry": {"coordinates":[-169.91138000000001,-19.12449],"type":"Point"}
}