{
  "type": "Feature",
  "properties": {
    "gn:asciiname":"Takaoga",
    "gn:country_code":"NU",
    "gn:dem":70,
    "gn:feature_class":"P",
    "gn:feature_code":"PPL",
    "gn:name":"Takaoga",
    "gn:population":0,
    "gn:timezone":"Pacific/Niue",
    "iso:country":"NU",
    "wof:name":"Takaoga",
    "wof:placetype":"locality"
},
  "geometry": {"coordinates":[-169.81009,-19.01555],"type":"Point"}
}